rlm_repl/__init__.py
rlm_repl/cli/__init__.py
rlm_repl/cli/main.py
rlm_repl/core/__init__.py
rlm_repl/core/config.py
rlm_repl/core/database.py
rlm_repl/core/repl.py
rlm_repl/events/__init__.py
rlm_repl/events/streaming.py
rlm_repl/inference/__init__.py
rlm_repl/inference/client.py
rlm_repl/inference/strategy.py
rlm_repl/inference/synthesizer.py
rlm_repl/utils/__init__.py
rlm_repl/utils/formatting.py
rlm_repl-0.1.0.dist-info/METADATA
rlm_repl-0.1.0.dist-info/WHEEL
rlm_repl-0.1.0.dist-info/entry_points.txt
rlm_repl-0.1.0.dist-info/RECORD
