Metadata-Version: 2.4
Name: rlm-repl
Version: 0.1.0
Summary: Recursive Language Model with REPL Inference Strategy - Unlimited context management using SQL-based retrieval
Project-URL: Homepage, https://github.com/labKnowledge/rlm-repl-sql
Project-URL: Documentation, https://github.com/labKnowledge/rlm-repl-sql#readme
Project-URL: Repository, https://github.com/labKnowledge/rlm-repl-sql
Project-URL: Issues, https://github.com/labKnowledge/rlm-repl-sql/issues
Author: Remy Gakwaya
License-Expression: MIT
Keywords: ai,context,duckdb,llm,nlp,rag,repl,retrieval,sql
Classifier: Development Status :: 4 - Beta
Classifier: Intended Audience :: Developers
Classifier: Intended Audience :: Science/Research
Classifier: License :: OSI Approved :: MIT License
Classifier: Operating System :: OS Independent
Classifier: Programming Language :: Python :: 3
Classifier: Programming Language :: Python :: 3.9
Classifier: Programming Language :: Python :: 3.10
Classifier: Programming Language :: Python :: 3.11
Classifier: Programming Language :: Python :: 3.12
Classifier: Topic :: Scientific/Engineering :: Artificial Intelligence
Classifier: Topic :: Text Processing
Requires-Python: >=3.9
Requires-Dist: duckdb>=0.9.0
Requires-Dist: openai>=1.0.0
Requires-Dist: pandas>=1.5.0
Provides-Extra: dev
Requires-Dist: mypy>=1.0.0; extra == 'dev'
Requires-Dist: pandas-stubs>=1.5.0; extra == 'dev'
Requires-Dist: pytest-cov>=4.0.0; extra == 'dev'
Requires-Dist: pytest>=7.0.0; extra == 'dev'
Requires-Dist: ruff>=0.1.0; extra == 'dev'
